sundate.py
sundate-0.0.1.dist-info/LICENSE
sundate-0.0.1.dist-info/METADATA
sundate-0.0.1.dist-info/WHEEL
sundate-0.0.1.dist-info/top_level.txt
sundate-0.0.1.dist-info/RECORD
