Metadata-Version: 2.1
Name: sundate
Version: 0.0.1
Summary: A module for convert jalali to gregorian And conversely & write now date
Home-page: UNKNOWN
Author: Armnajafi
License: UNKNOWN
Platform: UNKNOWN
Classifier: Programming Language :: Python :: 3
Classifier: License :: OSI Approved :: MIT License
Classifier: Operating System :: OS Independent
Requires-Python: >=3.6
